{"result": true, "cable": {"r4": {"lines": "X_PWR_EN -> X_RESETb", "Passed": true, "value": 12.089085578918457, "SD": 0.0006221765685415215}, "r5": {"lines": "VMON_REF1 -> WAGON_TYPE", "Passed": true, "value": 11.580437421798706, "SD": 0.0011250129990683123}, "r2": {"lines": "VMON_REF0 -> PROBE_DC", "Passed": true, "value": 64.29421901702881, "SD": 0.0038105972429520033}, "r3": {"lines": "VMON_REF2 -> PROBE_DC", "Passed": true, "value": 39.45662975311279, "SD": 0.0009261572170045391}}, "time": "2022-12-08 17:26:27 UTC"}